{
    "props": {
        "pageProps": {
            "card": {
                "title": "WeWow",
                "userId": "yoto",
                "availability": "free",
                "content": {
                    "version": "1",
                    "activity": "yoto_Player",
                    "config": {
                        "resumeTimeout": 2592000,
                        "onlineOnly": true
                    },
                    "availability": "",
                    "cover": {
                        "imageL": "https://card-content.yotoplay.com/1yZaK3MqE6IZfXfNILO4sYgdM9WYYILcUkyoLAtrnaOeO5jmiSlthHkA1GC19kUCw/pub/IpqYJNOf88eimw1alPEB2SdjGjurqHz1UmjDWsAJ1ZA"
                    },
                    "playbackType": "linear",
                    "editSettings": {
                        "transcodeAudioUploads": true,
                        "podcastType": "rss-podcast",
                        "contentType": "rss-podcast"
                    },
                    "chapters": [
                        {
                            "duration": 1186,
                            "overlayLabel": "NOV-03",
                            "title": "WeWow on the Weekend (11/3/24)",
                            "key": "f4cb7ec12d55fd949adc3e",
                            "display": {
                                "icon16x16": "https://card-content.yotoplay.com/yoto/jmpBDOfiG-5QDXND7NMAy9COAy1QJbM3AofqCy_BYX4"
                            },
                            "tracks": [
                                {
                                    "duration": 1186,
                                    "overlayLabel": "NOV-03",
                                    "format": "mp3",
                                    "title": "WeWow on the Weekend (11/3/24)",
                                    "type": "stream",
                                    "trackUrl": "https://dts.podtrac.com/redirect.mp3/chtbl.com/track/9EE2G/pdst.fm/e/rss.art19.com/episodes/74b4c941-8a5c-4331-89ef-5321338c88c3.mp3?rss_browser=BAhJIgpheGlvcwY6BkVU--e99fc5b28fa309118a966edfeec44f914ce607f1",
                                    "key": "f4cb7ec12d55fd949adc3e",
                                    "display": {
                                        "icon16x16": "https://card-content.yotoplay.com/yoto/jmpBDOfiG-5QDXND7NMAy9COAy1QJbM3AofqCy_BYX4"
                                    }
                                }
                            ]
                        },
                        {
                            "duration": 1272,
                            "overlayLabel": "NOV-02",
                            "title": "WeWow on the Weekend (11/2/24)",
                            "key": "2fc8b2ba69f74c2bc11eda",
                            "display": {
                                "icon16x16": "https://card-content.yotoplay.com/yoto/jmpBDOfiG-5QDXND7NMAy9COAy1QJbM3AofqCy_BYX4"
                            },
                            "tracks": [
                                {
                                    "duration": 1272,
                                    "overlayLabel": "NOV-02",
                                    "format": "mp3",
                                    "title": "WeWow on the Weekend (11/2/24)",
                                    "type": "stream",
                                    "trackUrl": "https://dts.podtrac.com/redirect.mp3/chtbl.com/track/9EE2G/pdst.fm/e/rss.art19.com/episodes/e2f398b0-999b-472e-834e-1e604f63bbc7.mp3?rss_browser=BAhJIgpheGlvcwY6BkVU--e99fc5b28fa309118a966edfeec44f914ce607f1",
                                    "key": "2fc8b2ba69f74c2bc11eda",
                                    "display": {
                                        "icon16x16": "https://card-content.yotoplay.com/yoto/jmpBDOfiG-5QDXND7NMAy9COAy1QJbM3AofqCy_BYX4"
                                    }
                                }
                            ]
                        },
                        {
                            "duration": 920,
                            "overlayLabel": "OCT-27",
                            "title": "WeWow on the Weekend (10/27/24)",
                            "key": "f089c07bf48f6b2e8a35e0",
                            "display": {
                                "icon16x16": "https://card-content.yotoplay.com/yoto/jmpBDOfiG-5QDXND7NMAy9COAy1QJbM3AofqCy_BYX4"
                            },
                            "tracks": [
                                {
                                    "duration": 920,
                                    "overlayLabel": "OCT-27",
                                    "format": "mp3",
                                    "title": "WeWow on the Weekend (10/27/24)",
                                    "type": "stream",
                                    "trackUrl": "https://dts.podtrac.com/redirect.mp3/chtbl.com/track/9EE2G/pdst.fm/e/rss.art19.com/episodes/24cbdb36-7b22-4ab9-ae77-3371c04171a3.mp3?rss_browser=BAhJIgpheGlvcwY6BkVU--e99fc5b28fa309118a966edfeec44f914ce607f1",
                                    "key": "f089c07bf48f6b2e8a35e0",
                                    "display": {
                                        "icon16x16": "https://card-content.yotoplay.com/yoto/jmpBDOfiG-5QDXND7NMAy9COAy1QJbM3AofqCy_BYX4"
                                    }
                                }
                            ]
                        },
                        {
                            "duration": 897,
                            "overlayLabel": "OCT-26",
                            "title": "WeWow on the Weekend (10/26/24)",
                            "key": "b4c3c9498a02645f470e7f",
                            "display": {
                                "icon16x16": "https://card-content.yotoplay.com/yoto/jmpBDOfiG-5QDXND7NMAy9COAy1QJbM3AofqCy_BYX4"
                            },
                            "tracks": [
                                {
                                    "duration": 897,
                                    "overlayLabel": "OCT-26",
                                    "format": "mp3",
                                    "title": "WeWow on the Weekend (10/26/24)",
                                    "type": "stream",
                                    "trackUrl": "https://dts.podtrac.com/redirect.mp3/chtbl.com/track/9EE2G/pdst.fm/e/rss.art19.com/episodes/49ecffb2-0813-4b54-874a-37bcf91b8a32.mp3?rss_browser=BAhJIgpheGlvcwY6BkVU--e99fc5b28fa309118a966edfeec44f914ce607f1",
                                    "key": "b4c3c9498a02645f470e7f",
                                    "display": {
                                        "icon16x16": "https://card-content.yotoplay.com/yoto/jmpBDOfiG-5QDXND7NMAy9COAy1QJbM3AofqCy_BYX4"
                                    }
                                }
                            ]
                        },
                        {
                            "duration": 1555,
                            "overlayLabel": "OCT-25",
                            "title": "WeWow Creepy Crawly Week 2024 - Day 5: Roach Revue (10/25/24)",
                            "key": "bf7c0d6e8e1164f07da2a1",
                            "display": {
                                "icon16x16": "https://card-content.yotoplay.com/yoto/jmpBDOfiG-5QDXND7NMAy9COAy1QJbM3AofqCy_BYX4"
                            },
                            "tracks": [
                                {
                                    "duration": 1555,
                                    "overlayLabel": "OCT-25",
                                    "format": "mp3",
                                    "title": "WeWow Creepy Crawly Week 2024 - Day 5: Roach Revue (10/25/24)",
                                    "type": "stream",
                                    "trackUrl": "https://dts.podtrac.com/redirect.mp3/chtbl.com/track/9EE2G/pdst.fm/e/rss.art19.com/episodes/35758ba6-3836-4f89-8839-8c9e43b2347f.mp3?rss_browser=BAhJIgpheGlvcwY6BkVU--e99fc5b28fa309118a966edfeec44f914ce607f1",
                                    "key": "bf7c0d6e8e1164f07da2a1",
                                    "display": {
                                        "icon16x16": "https://card-content.yotoplay.com/yoto/jmpBDOfiG-5QDXND7NMAy9COAy1QJbM3AofqCy_BYX4"
                                    }
                                }
                            ]
                        },
                        {
                            "duration": 1715,
                            "overlayLabel": "OCT-24",
                            "title": "WeWow Creepy Crawly Week 2024 - Day 4: The Return of Spider-Spider (10/24/24)",
                            "key": "374b5e0d07df934805b436",
                            "display": {
                                "icon16x16": "https://card-content.yotoplay.com/yoto/jmpBDOfiG-5QDXND7NMAy9COAy1QJbM3AofqCy_BYX4"
                            },
                            "tracks": [
                                {
                                    "duration": 1715,
                                    "overlayLabel": "OCT-24",
                                    "format": "mp3",
                                    "title": "WeWow Creepy Crawly Week 2024 - Day 4: The Return of Spider-Spider (10/24/24)",
                                    "type": "stream",
                                    "trackUrl": "https://dts.podtrac.com/redirect.mp3/chtbl.com/track/9EE2G/pdst.fm/e/rss.art19.com/episodes/79aabd37-16de-4aa8-82d7-2bf7de0110d9.mp3?rss_browser=BAhJIgpheGlvcwY6BkVU--e99fc5b28fa309118a966edfeec44f914ce607f1",
                                    "key": "374b5e0d07df934805b436",
                                    "display": {
                                        "icon16x16": "https://card-content.yotoplay.com/yoto/jmpBDOfiG-5QDXND7NMAy9COAy1QJbM3AofqCy_BYX4"
                                    }
                                }
                            ]
                        },
                        {
                            "duration": 1604,
                            "overlayLabel": "OCT-23",
                            "title": "WeWow Creepy Crawly Week 2024 - Day 3: Dennis’s Pest-aurant (10/23/24)",
                            "key": "4ba1f52ec228b6a6541c18",
                            "display": {
                                "icon16x16": "https://card-content.yotoplay.com/yoto/jmpBDOfiG-5QDXND7NMAy9COAy1QJbM3AofqCy_BYX4"
                            },
                            "tracks": [
                                {
                                    "duration": 1604,
                                    "overlayLabel": "OCT-23",
                                    "format": "mp3",
                                    "title": "WeWow Creepy Crawly Week 2024 - Day 3: Dennis’s Pest-aurant (10/23/24)",
                                    "type": "stream",
                                    "trackUrl": "https://dts.podtrac.com/redirect.mp3/chtbl.com/track/9EE2G/pdst.fm/e/rss.art19.com/episodes/7440b7fc-1c5f-4c63-b152-56dff042f083.mp3?rss_browser=BAhJIgpheGlvcwY6BkVU--e99fc5b28fa309118a966edfeec44f914ce607f1",
                                    "key": "4ba1f52ec228b6a6541c18",
                                    "display": {
                                        "icon16x16": "https://card-content.yotoplay.com/yoto/jmpBDOfiG-5QDXND7NMAy9COAy1QJbM3AofqCy_BYX4"
                                    }
                                }
                            ]
                        },
                        {
                            "duration": 1438,
                            "overlayLabel": "OCT-22",
                            "title": "WeWow Creepy Crawly Week 2024 - Day 2: Bugs of Steel (10/22/24)",
                            "key": "abf841f063021c9ef0bacd",
                            "display": {
                                "icon16x16": "https://card-content.yotoplay.com/yoto/jmpBDOfiG-5QDXND7NMAy9COAy1QJbM3AofqCy_BYX4"
                            },
                            "tracks": [
                                {
                                    "duration": 1438,
                                    "overlayLabel": "OCT-22",
                                    "format": "mp3",
                                    "title": "WeWow Creepy Crawly Week 2024 - Day 2: Bugs of Steel (10/22/24)",
                                    "type": "stream",
                                    "trackUrl": "https://dts.podtrac.com/redirect.mp3/chtbl.com/track/9EE2G/pdst.fm/e/rss.art19.com/episodes/0d0da44f-6be2-41f1-be3d-bac83636dcd1.mp3?rss_browser=BAhJIgpheGlvcwY6BkVU--e99fc5b28fa309118a966edfeec44f914ce607f1",
                                    "key": "abf841f063021c9ef0bacd",
                                    "display": {
                                        "icon16x16": "https://card-content.yotoplay.com/yoto/jmpBDOfiG-5QDXND7NMAy9COAy1QJbM3AofqCy_BYX4"
                                    }
                                }
                            ]
                        },
                        {
                            "duration": 1387,
                            "overlayLabel": "OCT-21",
                            "title": "WeWow Creepy Crawly Week 2024 - Day 1: Bugs Are Gross! (10/21/24)",
                            "key": "437871f49b8f2825034d87",
                            "display": {
                                "icon16x16": "https://card-content.yotoplay.com/yoto/jmpBDOfiG-5QDXND7NMAy9COAy1QJbM3AofqCy_BYX4"
                            },
                            "tracks": [
                                {
                                    "duration": 1387,
                                    "overlayLabel": "OCT-21",
                                    "format": "mp3",
                                    "title": "WeWow Creepy Crawly Week 2024 - Day 1: Bugs Are Gross! (10/21/24)",
                                    "type": "stream",
                                    "trackUrl": "https://dts.podtrac.com/redirect.mp3/chtbl.com/track/9EE2G/pdst.fm/e/rss.art19.com/episodes/6c02ba25-e7c0-44d6-b290-2fd131b21f69.mp3?rss_browser=BAhJIgpheGlvcwY6BkVU--e99fc5b28fa309118a966edfeec44f914ce607f1",
                                    "key": "437871f49b8f2825034d87",
                                    "display": {
                                        "icon16x16": "https://card-content.yotoplay.com/yoto/jmpBDOfiG-5QDXND7NMAy9COAy1QJbM3AofqCy_BYX4"
                                    }
                                }
                            ]
                        },
                        {
                            "duration": 1231,
                            "overlayLabel": "OCT-20",
                            "title": "WeWow on the Weekend (10/20/24)",
                            "key": "5a3cf521a580af128ea8f9",
                            "display": {
                                "icon16x16": "https://card-content.yotoplay.com/yoto/jmpBDOfiG-5QDXND7NMAy9COAy1QJbM3AofqCy_BYX4"
                            },
                            "tracks": [
                                {
                                    "duration": 1231,
                                    "overlayLabel": "OCT-20",
                                    "format": "mp3",
                                    "title": "WeWow on the Weekend (10/20/24)",
                                    "type": "stream",
                                    "trackUrl": "https://dts.podtrac.com/redirect.mp3/chtbl.com/track/9EE2G/pdst.fm/e/rss.art19.com/episodes/dac4017d-7dcc-400e-8073-9fce9b087baa.mp3?rss_browser=BAhJIgpheGlvcwY6BkVU--e99fc5b28fa309118a966edfeec44f914ce607f1",
                                    "key": "5a3cf521a580af128ea8f9",
                                    "display": {
                                        "icon16x16": "https://card-content.yotoplay.com/yoto/jmpBDOfiG-5QDXND7NMAy9COAy1QJbM3AofqCy_BYX4"
                                    }
                                }
                            ]
                        },
                        {
                            "duration": 1357,
                            "overlayLabel": "OCT-19",
                            "title": "WeWow on the Weekend (10/19/24)",
                            "key": "3474666306084c1d482ad4",
                            "display": {
                                "icon16x16": "https://card-content.yotoplay.com/yoto/jmpBDOfiG-5QDXND7NMAy9COAy1QJbM3AofqCy_BYX4"
                            },
                            "tracks": [
                                {
                                    "duration": 1357,
                                    "overlayLabel": "OCT-19",
                                    "format": "mp3",
                                    "title": "WeWow on the Weekend (10/19/24)",
                                    "type": "stream",
                                    "trackUrl": "https://dts.podtrac.com/redirect.mp3/chtbl.com/track/9EE2G/pdst.fm/e/rss.art19.com/episodes/4558297b-405d-48a3-bd71-3cff3b65f7a4.mp3?rss_browser=BAhJIgpheGlvcwY6BkVU--e99fc5b28fa309118a966edfeec44f914ce607f1",
                                    "key": "3474666306084c1d482ad4",
                                    "display": {
                                        "icon16x16": "https://card-content.yotoplay.com/yoto/jmpBDOfiG-5QDXND7NMAy9COAy1QJbM3AofqCy_BYX4"
                                    }
                                }
                            ]
                        },
                        {
                            "duration": 853,
                            "overlayLabel": "OCT-13",
                            "title": "WeWow on the Weekend (10/13/24)",
                            "key": "7a709263dce31b47ac0ce7",
                            "display": {
                                "icon16x16": "https://card-content.yotoplay.com/yoto/jmpBDOfiG-5QDXND7NMAy9COAy1QJbM3AofqCy_BYX4"
                            },
                            "tracks": [
                                {
                                    "duration": 853,
                                    "overlayLabel": "OCT-13",
                                    "format": "mp3",
                                    "title": "WeWow on the Weekend (10/13/24)",
                                    "type": "stream",
                                    "trackUrl": "https://dts.podtrac.com/redirect.mp3/chtbl.com/track/9EE2G/pdst.fm/e/rss.art19.com/episodes/f610229e-d85f-470d-af91-774f91d93b2c.mp3?rss_browser=BAhJIgpheGlvcwY6BkVU--e99fc5b28fa309118a966edfeec44f914ce607f1",
                                    "key": "7a709263dce31b47ac0ce7",
                                    "display": {
                                        "icon16x16": "https://card-content.yotoplay.com/yoto/jmpBDOfiG-5QDXND7NMAy9COAy1QJbM3AofqCy_BYX4"
                                    }
                                }
                            ]
                        },
                        {
                            "duration": 816,
                            "overlayLabel": "OCT-12",
                            "title": "WeWow on the Weekend (10/12/24)",
                            "key": "586bcdba0c055c2eecec8a",
                            "display": {
                                "icon16x16": "https://card-content.yotoplay.com/yoto/jmpBDOfiG-5QDXND7NMAy9COAy1QJbM3AofqCy_BYX4"
                            },
                            "tracks": [
                                {
                                    "duration": 816,
                                    "overlayLabel": "OCT-12",
                                    "format": "mp3",
                                    "title": "WeWow on the Weekend (10/12/24)",
                                    "type": "stream",
                                    "trackUrl": "https://dts.podtrac.com/redirect.mp3/chtbl.com/track/9EE2G/pdst.fm/e/rss.art19.com/episodes/45779cc5-e219-4c5b-bcab-112c7c9ab286.mp3?rss_browser=BAhJIgpheGlvcwY6BkVU--e99fc5b28fa309118a966edfeec44f914ce607f1",
                                    "key": "586bcdba0c055c2eecec8a",
                                    "display": {
                                        "icon16x16": "https://card-content.yotoplay.com/yoto/jmpBDOfiG-5QDXND7NMAy9COAy1QJbM3AofqCy_BYX4"
                                    }
                                }
                            ]
                        },
                        {
                            "duration": 1124,
                            "overlayLabel": "OCT-06",
                            "title": "WeWow on the Weekend (10/6/24)",
                            "key": "d67e9947f0d374034c473b",
                            "display": {
                                "icon16x16": "https://card-content.yotoplay.com/yoto/jmpBDOfiG-5QDXND7NMAy9COAy1QJbM3AofqCy_BYX4"
                            },
                            "tracks": [
                                {
                                    "duration": 1124,
                                    "overlayLabel": "OCT-06",
                                    "format": "mp3",
                                    "title": "WeWow on the Weekend (10/6/24)",
                                    "type": "stream",
                                    "trackUrl": "https://dts.podtrac.com/redirect.mp3/chtbl.com/track/9EE2G/pdst.fm/e/rss.art19.com/episodes/35995a8a-db0b-4d38-9e79-544c7d9ef161.mp3?rss_browser=BAhJIgpheGlvcwY6BkVU--e99fc5b28fa309118a966edfeec44f914ce607f1",
                                    "key": "d67e9947f0d374034c473b",
                                    "display": {
                                        "icon16x16": "https://card-content.yotoplay.com/yoto/jmpBDOfiG-5QDXND7NMAy9COAy1QJbM3AofqCy_BYX4"
                                    }
                                }
                            ]
                        },
                        {
                            "duration": 781,
                            "overlayLabel": "OCT-05",
                            "title": "WeWow on the Weekend (10/5/24)",
                            "key": "e5d25053ba69a303243d21",
                            "display": {
                                "icon16x16": "https://card-content.yotoplay.com/yoto/jmpBDOfiG-5QDXND7NMAy9COAy1QJbM3AofqCy_BYX4"
                            },
                            "tracks": [
                                {
                                    "duration": 781,
                                    "overlayLabel": "OCT-05",
                                    "format": "mp3",
                                    "title": "WeWow on the Weekend (10/5/24)",
                                    "type": "stream",
                                    "trackUrl": "https://dts.podtrac.com/redirect.mp3/chtbl.com/track/9EE2G/pdst.fm/e/rss.art19.com/episodes/052cc5d0-3462-47d8-ad83-ac9eedba9f8f.mp3?rss_browser=BAhJIgpheGlvcwY6BkVU--e99fc5b28fa309118a966edfeec44f914ce607f1",
                                    "key": "e5d25053ba69a303243d21",
                                    "display": {
                                        "icon16x16": "https://card-content.yotoplay.com/yoto/jmpBDOfiG-5QDXND7NMAy9COAy1QJbM3AofqCy_BYX4"
                                    }
                                }
                            ]
                        },
                        {
                            "duration": 1069,
                            "overlayLabel": "SEP-29",
                            "title": "WeWow on the Weekend (9/29/24)",
                            "key": "527645a75f4051624e50e7",
                            "display": {
                                "icon16x16": "https://card-content.yotoplay.com/yoto/jmpBDOfiG-5QDXND7NMAy9COAy1QJbM3AofqCy_BYX4"
                            },
                            "tracks": [
                                {
                                    "duration": 1069,
                                    "overlayLabel": "SEP-29",
                                    "format": "mp3",
                                    "title": "WeWow on the Weekend (9/29/24)",
                                    "type": "stream",
                                    "trackUrl": "https://dts.podtrac.com/redirect.mp3/chtbl.com/track/9EE2G/pdst.fm/e/rss.art19.com/episodes/f14d6492-358a-48af-8ef8-9e21a642f125.mp3?rss_browser=BAhJIgpheGlvcwY6BkVU--e99fc5b28fa309118a966edfeec44f914ce607f1",
                                    "key": "527645a75f4051624e50e7",
                                    "display": {
                                        "icon16x16": "https://card-content.yotoplay.com/yoto/jmpBDOfiG-5QDXND7NMAy9COAy1QJbM3AofqCy_BYX4"
                                    }
                                }
                            ]
                        },
                        {
                            "duration": 848,
                            "overlayLabel": "SEP-28",
                            "title": "WeWow on the Weekend (9/28/24)",
                            "key": "f7ad47bd7a31a991c73cd6",
                            "display": {
                                "icon16x16": "https://card-content.yotoplay.com/yoto/jmpBDOfiG-5QDXND7NMAy9COAy1QJbM3AofqCy_BYX4"
                            },
                            "tracks": [
                                {
                                    "duration": 848,
                                    "overlayLabel": "SEP-28",
                                    "format": "mp3",
                                    "title": "WeWow on the Weekend (9/28/24)",
                                    "type": "stream",
                                    "trackUrl": "https://dts.podtrac.com/redirect.mp3/chtbl.com/track/9EE2G/pdst.fm/e/rss.art19.com/episodes/f502e769-8aac-4bf7-9d9a-5a5cd193cb98.mp3?rss_browser=BAhJIgpheGlvcwY6BkVU--e99fc5b28fa309118a966edfeec44f914ce607f1",
                                    "key": "f7ad47bd7a31a991c73cd6",
                                    "display": {
                                        "icon16x16": "https://card-content.yotoplay.com/yoto/jmpBDOfiG-5QDXND7NMAy9COAy1QJbM3AofqCy_BYX4"
                                    }
                                }
                            ]
                        },
                        {
                            "duration": 1824,
                            "overlayLabel": "SEP-22",
                            "title": "WeWow on the Weekend (9/22/24)",
                            "key": "67e5bedc56e88fdb8b699a",
                            "display": {
                                "icon16x16": "https://card-content.yotoplay.com/yoto/jmpBDOfiG-5QDXND7NMAy9COAy1QJbM3AofqCy_BYX4"
                            },
                            "tracks": [
                                {
                                    "duration": 1824,
                                    "overlayLabel": "SEP-22",
                                    "format": "mp3",
                                    "title": "WeWow on the Weekend (9/22/24)",
                                    "type": "stream",
                                    "trackUrl": "https://dts.podtrac.com/redirect.mp3/chtbl.com/track/9EE2G/pdst.fm/e/rss.art19.com/episodes/da73cbcb-6345-425a-a6c7-f8557553fbef.mp3?rss_browser=BAhJIgpheGlvcwY6BkVU--e99fc5b28fa309118a966edfeec44f914ce607f1",
                                    "key": "67e5bedc56e88fdb8b699a",
                                    "display": {
                                        "icon16x16": "https://card-content.yotoplay.com/yoto/jmpBDOfiG-5QDXND7NMAy9COAy1QJbM3AofqCy_BYX4"
                                    }
                                }
                            ]
                        },
                        {
                            "duration": 1372,
                            "overlayLabel": "SEP-21",
                            "title": "WeWow on the Weekend (9/21/24)",
                            "key": "d05a4abe09a2b82b4b5a63",
                            "display": {
                                "icon16x16": "https://card-content.yotoplay.com/yoto/jmpBDOfiG-5QDXND7NMAy9COAy1QJbM3AofqCy_BYX4"
                            },
                            "tracks": [
                                {
                                    "duration": 1372,
                                    "overlayLabel": "SEP-21",
                                    "format": "mp3",
                                    "title": "WeWow on the Weekend (9/21/24)",
                                    "type": "stream",
                                    "trackUrl": "https://dts.podtrac.com/redirect.mp3/chtbl.com/track/9EE2G/pdst.fm/e/rss.art19.com/episodes/a1442018-96c2-4faa-9e3c-16c067cd4f66.mp3?rss_browser=BAhJIgpheGlvcwY6BkVU--e99fc5b28fa309118a966edfeec44f914ce607f1",
                                    "key": "d05a4abe09a2b82b4b5a63",
                                    "display": {
                                        "icon16x16": "https://card-content.yotoplay.com/yoto/jmpBDOfiG-5QDXND7NMAy9COAy1QJbM3AofqCy_BYX4"
                                    }
                                }
                            ]
                        },
                        {
                            "duration": 1854,
                            "overlayLabel": "SEP-15",
                            "title": "WeWow on the Weekend (9/15/24)",
                            "key": "c6f5958c6cec4edb561af8",
                            "display": {
                                "icon16x16": "https://card-content.yotoplay.com/yoto/jmpBDOfiG-5QDXND7NMAy9COAy1QJbM3AofqCy_BYX4"
                            },
                            "tracks": [
                                {
                                    "duration": 1854,
                                    "overlayLabel": "SEP-15",
                                    "format": "mp3",
                                    "title": "WeWow on the Weekend (9/15/24)",
                                    "type": "stream",
                                    "trackUrl": "https://dts.podtrac.com/redirect.mp3/chtbl.com/track/9EE2G/pdst.fm/e/rss.art19.com/episodes/25ac376e-6f6a-45e5-9fcb-92d144d2408a.mp3?rss_browser=BAhJIgpheGlvcwY6BkVU--e99fc5b28fa309118a966edfeec44f914ce607f1",
                                    "key": "c6f5958c6cec4edb561af8",
                                    "display": {
                                        "icon16x16": "https://card-content.yotoplay.com/yoto/jmpBDOfiG-5QDXND7NMAy9COAy1QJbM3AofqCy_BYX4"
                                    }
                                }
                            ]
                        },
                        {
                            "duration": 1715,
                            "overlayLabel": "SEP-14",
                            "title": "WeWow on the Weekend (9/14/24)",
                            "key": "facb6e206456bc27eb02cc",
                            "display": {
                                "icon16x16": "https://card-content.yotoplay.com/yoto/jmpBDOfiG-5QDXND7NMAy9COAy1QJbM3AofqCy_BYX4"
                            },
                            "tracks": [
                                {
                                    "duration": 1715,
                                    "overlayLabel": "SEP-14",
                                    "format": "mp3",
                                    "title": "WeWow on the Weekend (9/14/24)",
                                    "type": "stream",
                                    "trackUrl": "https://dts.podtrac.com/redirect.mp3/chtbl.com/track/9EE2G/pdst.fm/e/rss.art19.com/episodes/a5c72c41-3064-4e3e-bdc1-879e9c44e3a8.mp3?rss_browser=BAhJIgpheGlvcwY6BkVU--e99fc5b28fa309118a966edfeec44f914ce607f1",
                                    "key": "facb6e206456bc27eb02cc",
                                    "display": {
                                        "icon16x16": "https://card-content.yotoplay.com/yoto/jmpBDOfiG-5QDXND7NMAy9COAy1QJbM3AofqCy_BYX4"
                                    }
                                }
                            ]
                        },
                        {
                            "duration": 1798,
                            "overlayLabel": "SEP-08",
                            "title": "WeWow on the Weekend (9/8/24)",
                            "key": "90db9c984f0b043b4f3eeb",
                            "display": {
                                "icon16x16": "https://card-content.yotoplay.com/yoto/jmpBDOfiG-5QDXND7NMAy9COAy1QJbM3AofqCy_BYX4"
                            },
                            "tracks": [
                                {
                                    "duration": 1798,
                                    "overlayLabel": "SEP-08",
                                    "format": "mp3",
                                    "title": "WeWow on the Weekend (9/8/24)",
                                    "type": "stream",
                                    "trackUrl": "https://dts.podtrac.com/redirect.mp3/chtbl.com/track/9EE2G/pdst.fm/e/rss.art19.com/episodes/9dbe10ce-5e52-463c-a491-ef642f00f046.mp3?rss_browser=BAhJIgpheGlvcwY6BkVU--e99fc5b28fa309118a966edfeec44f914ce607f1",
                                    "key": "90db9c984f0b043b4f3eeb",
                                    "display": {
                                        "icon16x16": "https://card-content.yotoplay.com/yoto/jmpBDOfiG-5QDXND7NMAy9COAy1QJbM3AofqCy_BYX4"
                                    }
                                }
                            ]
                        },
                        {
                            "duration": 1777,
                            "overlayLabel": "SEP-07",
                            "title": "WeWow on the Weekend (9/7/24)",
                            "key": "d29ac5b095ef0e029f6f5a",
                            "display": {
                                "icon16x16": "https://card-content.yotoplay.com/yoto/jmpBDOfiG-5QDXND7NMAy9COAy1QJbM3AofqCy_BYX4"
                            },
                            "tracks": [
                                {
                                    "duration": 1777,
                                    "overlayLabel": "SEP-07",
                                    "format": "mp3",
                                    "title": "WeWow on the Weekend (9/7/24)",
                                    "type": "stream",
                                    "trackUrl": "https://dts.podtrac.com/redirect.mp3/chtbl.com/track/9EE2G/pdst.fm/e/rss.art19.com/episodes/16c8fe0b-9b2e-43d1-b5af-ffaa34a0f88d.mp3?rss_browser=BAhJIgpheGlvcwY6BkVU--e99fc5b28fa309118a966edfeec44f914ce607f1",
                                    "key": "d29ac5b095ef0e029f6f5a",
                                    "display": {
                                        "icon16x16": "https://card-content.yotoplay.com/yoto/jmpBDOfiG-5QDXND7NMAy9COAy1QJbM3AofqCy_BYX4"
                                    }
                                }
                            ]
                        },
                        {
                            "duration": 1567,
                            "overlayLabel": "AUG-11",
                            "title": "WeWow on the Weekend (8/11/24)",
                            "key": "4592383e927e21c133b35d",
                            "display": {
                                "icon16x16": "https://card-content.yotoplay.com/yoto/jmpBDOfiG-5QDXND7NMAy9COAy1QJbM3AofqCy_BYX4"
                            },
                            "tracks": [
                                {
                                    "duration": 1567,
                                    "overlayLabel": "AUG-11",
                                    "format": "mp3",
                                    "title": "WeWow on the Weekend (8/11/24)",
                                    "type": "stream",
                                    "trackUrl": "https://dts.podtrac.com/redirect.mp3/chtbl.com/track/9EE2G/pdst.fm/e/rss.art19.com/episodes/9ee396ac-9e97-4463-987c-5e9dd525f1bd.mp3?rss_browser=BAhJIgpheGlvcwY6BkVU--e99fc5b28fa309118a966edfeec44f914ce607f1",
                                    "key": "4592383e927e21c133b35d",
                                    "display": {
                                        "icon16x16": "https://card-content.yotoplay.com/yoto/jmpBDOfiG-5QDXND7NMAy9COAy1QJbM3AofqCy_BYX4"
                                    }
                                }
                            ]
                        },
                        {
                            "duration": 1645,
                            "overlayLabel": "AUG-10",
                            "title": "WeWow on the Weekend (8/10/24)",
                            "key": "0fc6ade8f23952a92a3d5a",
                            "display": {
                                "icon16x16": "https://card-content.yotoplay.com/yoto/jmpBDOfiG-5QDXND7NMAy9COAy1QJbM3AofqCy_BYX4"
                            },
                            "tracks": [
                                {
                                    "duration": 1645,
                                    "overlayLabel": "AUG-10",
                                    "format": "mp3",
                                    "title": "WeWow on the Weekend (8/10/24)",
                                    "type": "stream",
                                    "trackUrl": "https://dts.podtrac.com/redirect.mp3/chtbl.com/track/9EE2G/pdst.fm/e/rss.art19.com/episodes/e8764898-f0b6-468f-a9c9-85875f2da897.mp3?rss_browser=BAhJIgpheGlvcwY6BkVU--e99fc5b28fa309118a966edfeec44f914ce607f1",
                                    "key": "0fc6ade8f23952a92a3d5a",
                                    "display": {
                                        "icon16x16": "https://card-content.yotoplay.com/yoto/jmpBDOfiG-5QDXND7NMAy9COAy1QJbM3AofqCy_BYX4"
                                    }
                                }
                            ]
                        }
                    ]
                },
                "metadata": {
                    "feedUrl": "https://rss.art19.com/camp-wewow",
                    "lastBuildDate": "2023-08-08T12:30:38.084Z",
                    "category": "podcast",
                    "description": "From the award-winning creators behind kids podcast Wow in the World, WeWow is a variety show featuring all of your favorite characters from across Tinkercast’s podcasts. From WeWow on the Weekend hosted by your favorite nosy neighbor Dennis to week-long WeWow’s with daily STEAM activities, every episode of WeWow encourages curious kids to engage with all the WOW in the world.\n\nThis podcast contains ads. Yoto does not control these ads and they do not represent us or our opinions. Please listen with care.",
                    "author": "Wondery",
                    "imageUrl": "https://content.production.cdn.art19.com/images/e0/ba/41/4d/e0ba414d-7805-4435-bcdb-87ef5ccab9a1/691a811caac396f37cd22c10e2678fb525001a5dba2e8c15393d2ff76d3ec64b3b8fc62f8deba6c23f898a43ac812cea350a3c4798f4ab43bb6882b014d36fb4.jpeg",
                    "previewAudio": "https://cdn.shopify.com/s/files/1/0051/8845/2401/files/undefined.mp3",
                    "cover": {
                        "imageL": "https://card-content.yotoplay.com/1yZaK3MqE6IZfXfNILO4sYgdM9WYYILcUkyoLAtrnaOeO5jmiSlthHkA1GC19kUCw/pub/IpqYJNOf88eimw1alPEB2SdjGjurqHz1UmjDWsAJ1ZA"
                    },
                    "media": {
                        "duration": 0,
                        "fileSize": 0
                    },
                    "status": {
                        "name": "complete",
                        "updatedAt": "2023-08-08T12:30:42.859Z"
                    },
                    "languages": [
                        "en"
                    ]
                },
                "cardId": "jlhh9",
                "createdAt": "2023-08-08T12:32:38.357Z",
                "updatedAt": "2024-11-03T12:09:32.947Z",
                "lastCheckedAt": "2024-11-07T12:24:32.753Z"
            },
            "__ni18n_server__": {
                "resources": {
                    "en": {
                        "translation": {
                            "web_share_player_content_created_by": "created by",
                            "web_share_player_download_app_store": "Download on the App Store",
                            "web_share_player_download_app_tip_desktop": "Download the free Yoto App and scan this code",
                            "web_share_player_download_app_tip_generic": "Unlock a world of stories, music, activities, sleep sounds, podcasts and radio",
                            "web_share_player_download_app_tip_mobile": "Download the free Yoto App and tap the share link again",
                            "web_share_player_download_app_tip_nfc_tap": "Download the free Yoto App and tap the card on your mobile",
                            "web_share_player_download_app_title_add_card": "Want to add this card to your Yoto library?",
                            "web_share_player_download_app_title_generic": "Download the free Yoto App",
                            "web_share_player_download_google_play": "Get it on Google Play",
                            "web_share_player_invalid_link_desc": "It might contain a typo or is no longer available.",
                            "web_share_player_invalid_link_title": "Unrecognized link",
                            "web_share_player_link_preview_description": "Listen and add to your Yoto library",
                            "web_share_player_link_preview_num_of_episodes": "Number of episodes",
                            "web_share_player_link_preview_running_time": "Running time",
                            "web_share_player_link_preview_shared_by": "Shared by",
                            "web_share_player_not_found_heading": "Uh oh, I’ve got a bad feeling about this...",
                            "web_share_player_not_found_page_title": "Not found",
                            "web_share_player_not_found_text": "We can’t find the content you’re looking for. You might have followed an expired or invalid link.",
                            "web_share_player_sharing_paused_desc": "We’ve frozen this link because it may be breaking our <1>sharing policy</1>. The playlist’s creator can email hello@yotoplay.com to request a manual review.",
                            "web_share_player_sharing_paused_title": "Sharing paused",
                            "web_share_player_sharing_policy_url": "https://support.yotoplay.com/en-US/friends-and-family-safe-sharing-policy-11561"
                        }
                    },
                    "fr": {
                        "translation": {
                            "web_share_player_content_created_by": "Créé par",
                            "web_share_player_download_app_store": "Télécharger dans l'App Store",
                            "web_share_player_download_app_tip_desktop": "Téléchargez l'appli Yoto gratuite, puis scannez ce code",
                            "web_share_player_download_app_tip_generic": "Un univers audio fascinant : histoires, musique, bruits blancs, podcasts et radio",
                            "web_share_player_download_app_tip_mobile": "Téléchargez l'appli Yoto gratuite, puis appuyez de nouveau sur le lien partagé",
                            "web_share_player_download_app_tip_nfc_tap": "Téléchargez l'appli Yoto gratuite et tapez la carte sur votre téléphone pour l'écouter",
                            "web_share_player_download_app_title_add_card": "Souhaitez-vous ajouter cette carte dans votre audiothèque ?",
                            "web_share_player_download_app_title_generic": "Téléchargez l'appli Yoto gratuitement",
                            "web_share_player_download_google_play": "Disponible sur Google Play",
                            "web_share_player_invalid_link_title": "Lien non reconnu",
                            "web_share_player_link_preview_description": "Écouter et ajouter dans votre audiothèque",
                            "web_share_player_link_preview_num_of_episodes": "Nombre d'épisodes",
                            "web_share_player_link_preview_running_time": "Temps d'écoute",
                            "web_share_player_link_preview_shared_by": "Partagé par",
                            "web_share_player_not_found_heading": "Aïe, aïe, aïe… Ça, on ne l’avait pas prévu !",
                            "web_share_player_not_found_page_title": "Non trouvé",
                            "web_share_player_not_found_text": "Nous ne trouvons pas le contenu audio que vous cherchez. Vous avez peut-être ouvert un lien invalide ou un lien expiré.",
                            "web_share_player_sharing_paused_desc": "Nous avons gelé ce lien car il pourrait enfreindre notre <1>politique de partage<\\/1>. Le créateur du contenu peut nous contacter sur bonjour@yotoplay.com pour revoir le contenu.",
                            "web_share_player_sharing_paused_title": "Partage en pause",
                            "web_share_player_sharing_policy_url": "https://support.yotoplay.com/fr-FR/partager-du-contenu-audio-avec-vos-proches-11561"
                        }
                    }
                },
                "ns": [
                    "translation"
                ],
                "lng": "en"
            },
            "isPhysicalCard": true,
            "deviceLocale": "en",
            "deviceType": "desktop",
            "contentId": "jlhh9"
        },
        "__N_SSP": true
    },
    "page": "/p/[contentId]",
    "buildId": "V3pEs2QsEdVL4U035yoUs",
    "isFallback": false,
    "gssp": true,
    "scriptLoader": [],
    "officiality": {
        "version": "1",
        "date": "2024-11-07_09-19-58",
        "creator": "Yoto"
    }
}